moog/__init__.py
moog/environment.py
moog/polygons.py
moog/shapes.py
moog/sprite.py
moog/action_spaces/__init__.py
moog/action_spaces/abstract_action_space.py
moog/action_spaces/composite.py
moog/action_spaces/grid.py
moog/action_spaces/joystick.py
moog/action_spaces/set_position.py
moog/env_wrappers/__init__.py
moog/env_wrappers/abstract_wrapper.py
moog/env_wrappers/gym_wrapper.py
moog/env_wrappers/logger.py
moog/env_wrappers/multi_agent.py
moog/env_wrappers/simulation.py
moog/game_rules/__init__.py
moog/game_rules/abstract_rule.py
moog/game_rules/change_layer.py
moog/game_rules/conditional.py
moog/game_rules/contact_rules.py
moog/game_rules/create_sprites.py
moog/game_rules/fixation.py
moog/game_rules/modify_meta_state.py
moog/game_rules/modify_sprites.py
moog/game_rules/portal.py
moog/game_rules/re_center.py
moog/game_rules/task_phases.py
moog/game_rules/timing.py
moog/game_rules/vanish.py
moog/maze_lib/__init__.py
moog/maze_lib/maze.py
moog/maze_lib/maze_generators.py
moog/observers/__init__.py
moog/observers/abstract_observer.py
moog/observers/color_maps.py
moog/observers/pil_renderer.py
moog/observers/polygon_modifiers.py
moog/observers/raw_state.py
moog/physics/__init__.py
moog/physics/abstract_force.py
moog/physics/abstract_physics.py
moog/physics/collisions.py
moog/physics/constant_speed.py
moog/physics/distance_fn_force.py
moog/physics/friction.py
moog/physics/gravity.py
moog/physics/maze_physics.py
moog/physics/maze_walk.py
moog/physics/physics.py
moog/physics/random_force.py
moog/physics/tether_physics.py
moog/state_initialization/__init__.py
moog/state_initialization/distributions.py
moog/state_initialization/sprite_generators.py
moog/tasks/__init__.py
moog/tasks/abstract_task.py
moog/tasks/composite_task.py
moog/tasks/contact_reward.py
moog/tasks/reset.py
moog/tasks/stay_alive.py
moog_demos/__init__.py
moog_demos/gif_writer.py
moog_demos/gui_frames.py
moog_demos/human_agent.py
moog_demos/restore_logged_data.py
moog_demos/run_demo.py
moog_games-1.7.dist-info/LICENSE
moog_games-1.7.dist-info/LICENSE-spriteworld
moog_games-1.7.dist-info/METADATA
moog_games-1.7.dist-info/WHEEL
moog_games-1.7.dist-info/top_level.txt
moog_games-1.7.dist-info/RECORD
