Metadata-Version: 2.2
Name: moog-games
Version: 1.7
Summary: Modular object oriented games utils is a python-based game engine.
Home-page: https://github.com/jazlab/moog.github.io
Author: Nicholas Watters
License: MIT license
Keywords: ai,reinforcement-learning,python,machine learning,objects,psychology,neurophysiology,psychophysics,physics,environment
Classifier: Development Status :: 3 - Alpha
Classifier: Environment :: Console
Classifier: Intended Audience :: Science/Research
Classifier: License :: OSI Approved :: MIT License
Classifier: Operating System :: POSIX :: Linux
Classifier: Operating System :: Microsoft :: Windows
Classifier: Operating System :: MacOS :: MacOS X
Classifier: Programming Language :: Python :: 3.7
Classifier: Programming Language :: Python :: 3.8
Classifier: Topic :: Scientific/Engineering
License-File: LICENSE
License-File: LICENSE-spriteworld
Requires-Dist: cmake
Requires-Dist: numpy==2.2.3
Requires-Dist: matplotlib==3.10.0
Requires-Dist: imageio==2.37.0
Requires-Dist: mss==10.0.0
Requires-Dist: tqdm==4.67.1
Requires-Dist: dm_env==1.6
Requires-Dist: gym==0.26.2
Dynamic: author
Dynamic: classifier
Dynamic: description
Dynamic: description-content-type
Dynamic: home-page
Dynamic: keywords
Dynamic: license
Dynamic: requires-dist
Dynamic: summary
